gi_docgen-2026.1.data/data/share/man/man1/gi-docgen.1
gi_docgen-2026.1.data/data/share/pkgconfig/gi-docgen.pc
gi_docgen-2026.1.dist-info/licenses/LICENSES/Apache-2.0.txt
gi_docgen-2026.1.dist-info/licenses/LICENSES/GPL-3.0-or-later.txt
gidocgen/__init__.py
gidocgen/config.py
gidocgen/core.py
gidocgen/gdcheck.py
gidocgen/gdgendeps.py
gidocgen/gdgenerate.py
gidocgen/gdgenindices.py
gidocgen/gdindex.py
gidocgen/gdsearch.py
gidocgen/gdserver.py
gidocgen/gidocmain.py
gidocgen/log.py
gidocgen/mdext.py
gidocgen/py.typed
gidocgen/utils.py
gidocgen/gir/__init__.py
gidocgen/gir/ast.py
gidocgen/gir/parser.py
gidocgen/templates/basic/RedHatDisplay-Black.woff
gidocgen/templates/basic/RedHatDisplay-Black.woff2
gidocgen/templates/basic/RedHatDisplay-BlackItalic.woff
gidocgen/templates/basic/RedHatDisplay-BlackItalic.woff2
gidocgen/templates/basic/RedHatDisplay-Bold.woff
gidocgen/templates/basic/RedHatDisplay-Bold.woff2
gidocgen/templates/basic/RedHatDisplay-BoldItalic.woff
gidocgen/templates/basic/RedHatDisplay-BoldItalic.woff2
gidocgen/templates/basic/RedHatDisplay-Italic.woff
gidocgen/templates/basic/RedHatDisplay-Italic.woff2
gidocgen/templates/basic/RedHatDisplay-Medium.woff
gidocgen/templates/basic/RedHatDisplay-Medium.woff2
gidocgen/templates/basic/RedHatDisplay-MediumItalic.woff
gidocgen/templates/basic/RedHatDisplay-MediumItalic.woff2
gidocgen/templates/basic/RedHatDisplay-Regular.woff
gidocgen/templates/basic/RedHatDisplay-Regular.woff2
gidocgen/templates/basic/RedHatText-Bold.woff
gidocgen/templates/basic/RedHatText-Bold.woff2
gidocgen/templates/basic/RedHatText-BoldItalic.woff
gidocgen/templates/basic/RedHatText-BoldItalic.woff2
gidocgen/templates/basic/RedHatText-Italic.woff
gidocgen/templates/basic/RedHatText-Italic.woff2
gidocgen/templates/basic/RedHatText-Medium.woff
gidocgen/templates/basic/RedHatText-Medium.woff2
gidocgen/templates/basic/RedHatText-MediumItalic.woff
gidocgen/templates/basic/RedHatText-MediumItalic.woff2
gidocgen/templates/basic/RedHatText-Regular.woff
gidocgen/templates/basic/RedHatText-Regular.woff2
gidocgen/templates/basic/SourceCodePro-It.ttf.woff
gi_docgen-2026.1.dist-info/METADATA
gi_docgen-2026.1.dist-info/WHEEL
gi_docgen-2026.1.dist-info/entry_points.txt
gi_docgen-2026.1.dist-info/top_level.txt
gi_docgen-2026.1.dist-info/RECORD
