Metadata-Version: 2.4
Name: gi-docgen
Version: 2026.1
Summary: Documentation tool for GObject-based libraries
Home-page: https://gitlab.gnome.org/GNOME/gi-docgen
Author: Emmanuele Bassi
Author-email: ebassi@gnome.org
License: GPL-3.0-or-later AND Apache-2.0 AND CC0-1.0
Project-URL: Bug tracker, https://gitlab.gnome.org/GNOME/gi-docgen/issues/
Project-URL: Documentation, https://gnome.pages.gitlab.gnome.org/gi-docgen/
Keywords: documentation,introspection,gobject,gtk
Classifier: Development Status :: 4 - Beta
Classifier: Environment :: Console
Classifier: Intended Audience :: Developers
Classifier: License :: OSI Approved :: Apache Software License
Classifier: License :: OSI Approved :: GNU General Public License v3 or later (GPLv3+)
Classifier: Natural Language :: English
Classifier: Operating System :: MacOS :: MacOS X
Classifier: Operating System :: Microsoft :: Windows
Classifier: Operating System :: POSIX :: BSD
Classifier: Operating System :: POSIX :: Linux
Classifier: Programming Language :: Python :: 3 :: Only
Classifier: Programming Language :: Python :: 3.6
Classifier: Programming Language :: Python :: 3.7
Classifier: Programming Language :: Python :: 3.8
Classifier: Programming Language :: Python :: 3.9
Classifier: Topic :: Desktop Environment :: Gnome
Classifier: Topic :: Software Development :: Documentation
Requires-Python: >=3.6.0
License-File: LICENSES/Apache-2.0.txt
License-File: LICENSES/GPL-3.0-or-later.txt
Requires-Dist: Markdown>=3.2
Requires-Dist: MarkupSafe
Requires-Dist: Pygments
Requires-Dist: jinja2
Requires-Dist: packaging
Requires-Dist: tomli; python_version < "3.11"
Requires-Dist: typogrify
Dynamic: license-file
